Metadata-Version: 1.1
Name: toutetu
Version: 1.0.2
Summary: 'Meals ordering tool'
Home-page: UNKNOWN
Author: Arthur Dayne
Author-email: UNKNOWN
License: UNKNOWN
Platform: UNKNOWN
Classifier: Programming Language :: Python :: 3
Classifier: Programming Language :: Python :: 3.6
Classifier: Programming Language :: Python :: 3.7
